ExoSOFT
