Metadata-Version: 1.1
Name: ExoSOFT
Version: 0.3.6
Summary: The Exoplanet Simple Orbit Fitting Toolbox (ExoSOFT)
Home-page: https://github.com/kylemede/ExoSOFT
Author: Kyle Mede
Author-email: kylemede@gmail.com
License: ['GNU GPLv3']
Platform: UNKNOWN
Classifier: Development Status :: 3 - Alpha
Classifier: Intended Audience :: Science/Research
Classifier: Topic :: Scientific/Engineering
Classifier: Programming Language :: Python
